{
    "company_name": "HERAMED LIMITED",
    "address": "Suite 4, Level 16 55 Clarence Street, SYDNEY, NSW, AUSTRALIA, 2000",
    "summary": "Development, manufacture and distribution of fetal heart beat monitors and other pregnancy-related solutions.",
    "details": "Development, manufacture and distribution of fetal heart beat monitors and other pregnancy-related solutions.",
    "website": "http://www.hera-med.com",
    "stock_code": "HMD",
    "links": "['https://www.hera-med.com', 'https://www.hera-med.com/about', 'https://www.hera-med.com/technology', 'https://www.hera-med.com/technology', 'https://www.hera-med.com/herabeat', 'https://www.hera-med.com/impact', 'https://www.hera-med.com/investor-relations', '', '', 'https://www.hera-med.com/technology', 'https://www.hera-med.com/technology', 'https://www.hera-med.com/technology', 'https://www.hera-med.com/news', 'https://www.hera-med.com/post/dr-ron-weinberger-executive-chairman-letter-to-shareholders', 'https://www.hera-med.com/post/dr-ron-weinberger-appointed-executive-chairman-letter-to-shareholders', 'https://www.hera-med.com/post/heracare-program-now-available-to-snap-inc-employees-and-their-family-members', '', 'https://www.hera-med.com/website-privacy-policy', 'https://www.hera-med.com/ccpa', 'https://www.hera-med.com/corporate-governance-plan', 'https://www.hera-med.com/corporate-governance-statement', 'https://www.hera-med.com/schedule-9-securities-trading-policy', 'https://www.hera-med.com/whistleblower-protection-policy', 'https://www.hera-med.com/accessibility-statement', 'https://www.hera-med.com/about', 'https://www.hera-med.com/technology', 'https://www.hera-med.com/technology', 'https://www.hera-med.com/herabeat', 'https://www.hera-med.com/impact', 'https://www.hera-med.com/investor-relations', 'https://www.hera-med.com', '', 'https://www.youtube.com/channel/UCAlTYsc6t6y01nW1NsexhXQ', 'https://www.linkedin.com/company/heramed/', 'https://twitter.com/HeraMED_ASX', 'https://www.hera-med.com/about', 'https://www.hera-med.com/technology', 'https://www.hera-med.com/technology', 'https://www.hera-med.com/herabeat', 'https://www.hera-med.com/impact', 'https://www.hera-med.com/investor-relations']",
    "images": "https://static.wixstatic.com/media/2b57d8_dcc161cfa3b4476986cdd761d26c0bec~mv2.png/v1/fill/w_49,h_28,al_c,q_85,usm_0.66_1.00_0.01,blur_2,enc_auto/HeraMED_Home_Header_FNL.png, https://static.wixstatic.com/media/3efff5_088208fc7142419a8de8c29ca035ae4e~mv2.png/v1/fill/w_89,h_102,al_c,q_85,usm_0.66_1.00_0.01,blur_2,enc_auto/HeraMED_Home_Header_FNL_MOBILE.png, https://static.wixstatic.com/media/2b57d8_164e6451142f45b181986d9141615d27~mv2.png/v1/fill/w_49,h_7,al_c,q_85,usm_0.66_1.00_0.01,blur_2,enc_auto/Home%201_edited.png, https://static.wixstatic.com/media/2b57d8_072c6bce1cf942aea7faf61b675fc7d5~mv2.png/v1/fill/w_91,h_322,al_c,q_85,usm_0.66_1.00_0.01,blur_2,enc_auto/home2.png, https://static.wixstatic.com/media/2b57d8_e6fa8a67483449a2801ef2661b60ec61~mv2.png/v1/fill/w_49,h_76,al_c,q_85,usm_0.66_1.00_0.01,blur_2,enc_auto/MOCK-UP_Mobile.png, https://static.wixstatic.com/media/2b57d8_a1b6346af38644ef9c5e374a1e4cc0cf~mv2.png/v1/fill/w_49,h_15,al_c,q_85,usm_0.66_1.00_0.01,blur_2,enc_auto/Home%201_edited.png, https://static.wixstatic.com/media/3efff5_17279d2922504098a5d6e5336602e14e~mv2.png/v1/fill/w_49,h_3,al_c,q_85,usm_0.66_1.00_0.01,blur_2,enc_auto/J01.png, https://static.wixstatic.com/media/2b57d8_479572a132634da7b39b7b65dd510d1c~mv2.png/v1/fill/w_91,h_322,al_c,q_85,usm_0.66_1.00_0.01,blur_2,enc_auto/mobile1.png, https://static.wixstatic.com/media/3efff5_54847da994f84742acced2504d9a56d5~mv2.png/v1/fill/w_49,h_22,al_c,q_85,usm_0.66_1.00_0.01,blur_2,enc_auto/Home_J2_01.png, https://static.wixstatic.com/media/3efff5_4b51690d7a314d61b0c38549125d3755~mv2.png/v1/fill/w_49,h_5,al_c,q_85,usm_0.66_1.00_0.01,blur_2,enc_auto/Home_J2_04.png, https://static.wixstatic.com/media/3efff5_35bb9952641746d6824aa7bc5ac9a1a6~mv2.png/v1/fill/w_49,h_5,al_c,q_85,usm_0.66_1.00_0.01,blur_2,enc_auto/Home_J2_02.png, https://static.wixstatic.com/media/3efff5_8e3d2b6222ce451686743a19c4be3584~mv2.png/v1/fill/w_49,h_4,al_c,q_85,usm_0.66_1.00_0.01,blur_2,enc_auto/Home_J2_03.png, https://static.wixstatic.com/media/3efff5_8e3d2b6222ce451686743a19c4be3584~mv2.png/v1/fill/w_49,h_4,al_c,q_85,usm_0.66_1.00_0.01,blur_2,enc_auto/Home_J2_03.png, https://static.wixstatic.com/media/e8bec9_f4e08d5e84c74a0a8c2e2ac6b8532bc0~mv2.png/v1/fill/w_49,h_19,al_c,q_85,usm_0.66_1.00_0.01,blur_2,enc_auto/HeraMED_Home_Connected%20Graphic_Desktop_FNL-Ariel%20copy.png, https://static.wixstatic.com/media/e8bec9_11829d70ec1a4f20bbeb8ad86242cc6a~mv2.png/v1/fill/w_49,h_76,al_c,q_85,usm_0.66_1.00_0.01,blur_2,enc_auto/HeraMED_Home_Connected%20Graphic_Molbile_FNL-Ariel%20copy.png, https://static.wixstatic.com/media/2b57d8_50e98d7d06004cb0aebab2304671d42d~mv2.png/v1/fill/w_49,h_6,al_c,q_85,usm_0.66_1.00_0.01,blur_2,enc_auto/HeraMED_Website%20Refresh_Home_FNL_Logos%20-%20Desktop-%20Ariel%2025-11-2023.png, https://static.wixstatic.com/media/2b57d8_5451d502ef7c45e5aa498e85ae8c32eb~mv2.png/v1/fill/w_49,h_20,al_c,q_85,usm_0.66_1.00_0.01,blur_2,enc_auto/HeraMED_Website%20Refresh_Home_FNL_Logos%20-%20Mobile%20-%20Ariel%2025-11-2023.png, https://static.wixstatic.com/media/2b57d8_3211c7e1e1de4b9aa1af76f73e2ca38d~mv2.png/v1/fill/w_91,h_534,al_c,q_85,usm_0.66_1.00_0.01,blur_2,enc_auto/homeJ5.png, https://static.wixstatic.com/media/2b57d8_03818e4299454bd8a6d65284e9a84762~mv2.png/v1/fill/w_160,h_416,al_c,q_85,blur_3,enc_auto/home5.png, https://static.wixstatic.com/media/3efff5_cd1a8daa0b194eee8e3fe922f7be17af~mv2.png/v1/fill/w_49,h_8,al_c,q_85,usm_0.66_1.00_0.01,blur_2,enc_auto/Home_J5_01.png, https://static.wixstatic.com/media/3efff5_bb223d9c636a4a96a056401bf289bff3~mv2.png/v1/fill/w_49,h_9,al_c,q_85,usm_0.66_1.00_0.01,blur_2,enc_auto/Home_J5_02.png, https://static.wixstatic.com/media/3efff5_1626b5fce88f40918f2741b3dde088b7~mv2.png/v1/fill/w_49,h_27,al_c,q_85,usm_0.66_1.00_0.01,blur_2,enc_auto/Home_J5_03.png, https://static.wixstatic.com/media/3efff5_7d31413e02ae44d8bc9b1fcb0af39699~mv2.png/v1/fill/w_49,h_27,al_c,q_85,usm_0.66_1.00_0.01,blur_2,enc_auto/Home_J5_04.png, https://static.wixstatic.com/media/2b57d8_cac85abe4be54e5e81eb9737b1caf359~mv2.png/v1/fill/w_91,h_210,al_c,q_85,usm_0.66_1.00_0.01,blur_2,enc_auto/home%205.png, https://static.wixstatic.com/media/2b57d8_70b260de07774ee5b87c65980f05c998~mv2.png/v1/fill/w_49,h_37,al_c,q_85,usm_0.66_1.00_0.01,blur_2,enc_auto/HeraCARE%20Kit%20-Home%20Page%20-%20Simple%20Setup.png, https://static.wixstatic.com/media/2b57d8_43d82b02b4d741f281448306f9019800~mv2.jpg/v1/crop/x_200,y_0,w_1124,h_1080/fill/w_86,h_83,al_c,q_80,usm_0.66_1.00_0.01,blur_2,enc_auto/Person%20Looking%20at%20Dashboard.jpg, https://static.wixstatic.com/media/2b57d8_893d8b22e37e4c10b346363d46914778~mv2.jpg/v1/fill/w_147,h_98,al_c,q_80,usm_0.66_1.00_0.01,blur_2,enc_auto/Easy%20to%20use.jpg, https://static.wixstatic.com/media/2b57d8_792acac14dd94f9c9168f72771f6ae77~mv2.png/v1/fill/w_149,h_300,al_c,q_85,blur_3,enc_auto/HeraCARE-App-IPhone%20Home%20-%20for%20easy%20to%20use%20section.png, https://static.wixstatic.com/media/2b57d8_38757a76e09c4dbfb10e67c330eb25b1~mv2.png/v1/fill/w_91,h_200,al_c,q_85,usm_0.66_1.00_0.01,blur_2,enc_auto/baby%20home.png, https://static.wixstatic.com/media/2b57d8_66193b5c33d349d5afcfe0e2e5f04509~mv2.png/v1/fill/w_91,h_129,al_c,q_85,usm_0.66_1.00_0.01,blur_2,enc_auto/home6.png, https://static.wixstatic.com/media/2b57d8_5cc711add6de4270aa17757a013fb637~mv2.png/v1/crop/x_62,y_0,w_1277,h_934/fill/w_46,h_34,al_c,q_85,usm_0.66_1.00_0.01,blur_2,enc_auto/home%206.png, https://static.wixstatic.com/media/2b57d8_c0005c9269244c95baad35b6f400b1fa~mv2.png/v1/fill/w_54,h_68,al_c,q_85,usm_0.66_1.00_0.01,blur_2,enc_auto/HeraMED_Website%20Refresh_Home_Icon%20-%2050%20Reduction%20in%20in-office%20visits.png, https://static.wixstatic.com/media/2b57d8_c712b9e6d5df4497b9a39791a2b470fb~mv2.png/v1/fill/w_60,h_60,al_c,q_85,usm_0.66_1.00_0.01,blur_2,enc_auto/HeraMED_Website%20Refresh_Home_Icon%20-%20High%20patient%20and%20provider%20satisfaction%20scores.png, https://static.wixstatic.com/media/2b57d8_ab8cd04dbe884c9aa560e073df32efef~mv2.png/v1/fill/w_62,h_61,al_c,q_85,usm_0.66_1.00_0.01,blur_2,enc_auto/HeraMED_Website%20Refresh_Home_Icon%20-%20Increased%20vital%20capture%20compared%20to%20traditional%20prenat.png, https://static.wixstatic.com/media/2b57d8_464053fcb0304d79882f9b795c6b4214~mv2.png/v1/fill/w_71,h_71,al_c,q_85,usm_0.66_1.00_0.01,blur_2,enc_auto/HeraMED_Website%20Refresh_Home_Icon%20-%20400000%20HeraBEAT%20measurements%20worldwide%20and%20growing%20dai.png, https://static.wixstatic.com/media/2b57d8_ab8cd04dbe884c9aa560e073df32efef~mv2.png/v1/fill/w_62,h_61,al_c,q_85,usm_0.66_1.00_0.01,blur_2,enc_auto/HeraMED_Website%20Refresh_Home_Icon%20-%20Increased%20vital%20capture%20compared%20to%20traditional%20prenat.png, https://static.wixstatic.com/media/e8bec9_bdfcd73f39464a3eb0cf405b9b438a01~mv2.png/v1/fill/w_49,h_28,al_c,q_85,usm_0.66_1.00_0.01,blur_2,enc_auto/HeraMED_Website%20Refresh_Home_FNL_Deashboard%20Screen-Ariel.png, https://static.wixstatic.com/media/2b57d8_08b0db36d56f4ff1b0d91bb1bf95a9fb~mv2.png/v1/fill/w_49,h_21,al_c,q_85,usm_0.66_1.00_0.01,blur_2,enc_auto/mobileJ7.png, https://static.wixstatic.com/media/2b57d8_0e29c39b09f44da4862da6595630e93a~mv2.png/v1/fill/w_92,h_102,al_c,q_85,usm_0.66_1.00_0.01,blur_2,enc_auto/home7.png, https://static.wixstatic.com/media/e8bec9_103334af6b0e4d95acd1d1847aa66097~mv2.jpg/v1/fill/w_147,h_114,al_c,q_80,usm_0.66_1.00_0.01,blur_2,enc_auto/e8bec9_103334af6b0e4d95acd1d1847aa66097~mv2.jpg, https://static.wixstatic.com/media/e8bec9_05373e32b19e4e28a25d14cddb41e4e6~mv2.jpg/v1/fill/w_100,h_100,al_c,q_80,usm_0.66_1.00_0.01,blur_2,enc_auto/e8bec9_05373e32b19e4e28a25d14cddb41e4e6~mv2.jpg, https://static.wixstatic.com/media/e03285_7b051a98c1ed46e1ba9ab02e2a57f53b~mv2.jpg/v1/fill/w_147,h_98,al_c,q_80,usm_0.66_1.00_0.01,blur_2,enc_auto/e03285_7b051a98c1ed46e1ba9ab02e2a57f53b~mv2.jpg, https://static.wixstatic.com/media/2b57d8_99ee044d08ed49db8624d08685e38642~mv2.png/v1/fill/w_84,h_133,al_c,q_85,usm_0.66_1.00_0.01,blur_2,enc_auto/home8_edited.png, https://static.wixstatic.com/media/2b57d8_3b15fb591b7645578842ff85aefcf0e9~mv2.png/v1/fill/w_49,h_30,al_c,q_85,usm_0.66_1.00_0.01,blur_2,enc_auto/mobileJ8_edited.png, https://static.wixstatic.com/media/2b57d8_da0ae99c3b7348e79cb1394e846396ea~mv2.png/v1/fill/w_100,h_100,al_c,q_85,usm_0.66_1.00_0.01,blur_2,enc_auto/1567089997246_R.png, https://static.wixstatic.com/media/2b57d8_f5f7ae6a11d747ca840c9a8e1de06d5d~mv2.jpg/v1/fill/w_77,h_91,al_c,q_80,usm_0.66_1.00_0.01,blur_2,enc_auto/Cliff-Neppe_edited.jpg, https://static.wixstatic.com/media/2b57d8_5fd4f3d4b42340669b3745a24c40a2f4~mv2.jpg/v1/fill/w_172,h_172,al_c,q_80,blur_3,enc_auto/paulporter_edited_edited.jpg, https://static.wixstatic.com/media/3efff5_d2f6fff3ab0c4ab6a7b591c57ef6d8b1~mv2.jpg/v1/fill/w_56,h_56,al_c,q_80,usm_0.66_1.00_0.01,blur_2,enc_auto/avitsur_edited_02.jpg, https://static.wixstatic.com/media/2b57d8_b11690fb44d7475590a620710d13f868~mv2.jpg/v1/fill/w_100,h_100,al_c,q_80,usm_0.66_1.00_0.01,blur_2,enc_auto/Galia_edited.jpg, https://static.wixstatic.com/media/2b57d8_ce2019bc2f7d436da4cc2b3617aec625~mv2.png/v1/fill/w_118,h_134,al_c,q_85,usm_0.66_1.00_0.01,blur_2,enc_auto/home%2012_edited.png, https://static.wixstatic.com/media/2b57d8_0743dc78d7fb4fc2b14a304c6a7ffda7~mv2.png/v1/fill/w_51,h_31,al_c,q_85,usm_0.66_1.00_0.01,blur_2,enc_auto/home9.png",
    "company_logo_link": "https://static.wixstatic.com/media/2b57d8_dcc161cfa3b4476986cdd761d26c0bec~mv2.png/v1/fill/w_49,h_28,al_c,q_85,usm_0.66_1.00_0.01,blur_2,enc_auto/HeraMED_Home_Header_FNL.png"
}