{
    "company_name": "SHAVER SHOP GROUP LIMITED",
    "address": "Level 1, Chadstone Tower One, 1341 Dandenong Road, CHADSTONE, VIC, AUSTRALIA, 3148",
    "summary": "Retail of personal grooming products",
    "details": "Retail of personal grooming products",
    "website": "http://shavershop.com.au",
    "stock_code": "SSG",
    "links": "['https://www.shavershop.com.au/delivery.html', 'https://www.shavershop.com.au/delivery.html', 'https://www.shavershop.com.au/delivery.html', 'https://www.shavershop.com.au/clickcollect', 'https://www.shavershop.com.au/sale/', 'https://www.shavershop.com.au/', 'https://www.shavershop.com.au/cart', '#', 'https://www.shavershop.com.au/cart', 'javascript:void(0);', '', 'https://www.shavershop.com.au/stores', 'https://www.shavershop.com.au/sale/', 'https://www.shavershop.com.au/sale/electric-shavers/', 'https://www.shavershop.com.au/sale/electric-shavers/', 'https://www.shavershop.com.au/sale/manual-shavers/', 'https://www.shavershop.com.au/sale/manual-shavers/', 'https://www.shavershop.com.au/sale/clippers-trimmers-groomers/', 'https://www.shavershop.com.au/sale/clippers-trimmers-groomers/', 'https://www.shavershop.com.au/sale/mens-skin-hair-care/', 'https://www.shavershop.com.au/sale/mens-skin-hair-care/', 'https://www.shavershop.com.au/sale/hair-removal/', 'https://www.shavershop.com.au/sale/hair-removal/', 'https://www.shavershop.com.au/sale/hair-styling/', 'https://www.shavershop.com.au/sale/hair-styling/', 'https://www.shavershop.com.au/sale/beauty/', 'https://www.shavershop.com.au/sale/beauty/', 'https://www.shavershop.com.au/sale/oral-care/', 'https://www.shavershop.com.au/sale/oral-care/', 'https://www.shavershop.com.au/sale/massage-wellness/', 'https://www.shavershop.com.au/sale/massage-wellness/', 'https://www.shavershop.com.au/sale/fragrance/', 'https://www.shavershop.com.au/sale/fragrance/', 'https://www.shavershop.com.au/men/', 'https://www.shavershop.com.au/electric-shavers-2/', 'https://www.shavershop.com.au/electric-shavers-2/', 'https://www.shavershop.com.au/electric-shavers/all-electric-shavers/', 'https://www.shavershop.com.au/electric-shavers/pre-shave-accessories/', 'https://www.shavershop.com.au/electric-shavers/post-shave-accessories/', 'https://www.shavershop.com.au/electric-shavers/replacement-parts-and-accessories/', 'https://www.shavershop.com.au/beard-trimmers/', 'https://www.shavershop.com.au/beard-trimmers/', 'https://www.shavershop.com.au/beard-trimmers/all-beard-trimmers/', 'https://www.shavershop.com.au/beard-trimmers/grooming-kits/', 'https://www.shavershop.com.au/beard-trimmers/nose-and-ear-trimmers/', 'https://www.shavershop.com.au/beard-trimmers/beard-care/', 'https://www.shavershop.com.au/beard-trimmers/beard-trimmer-parts-and-accessories/', 'https://www.shavershop.com.au/hair-clippers/', 'https://www.shavershop.com.au/hair-clippers/', 'https://www.shavershop.com.au/hair-clippers/all-hair-clippers/', 'https://www.shavershop.com.au/hair-clippers/guides-and-accessories/', 'https://www.shavershop.com.au/hair-clippers/scissors/', 'https://www.shavershop.com.au/hair-clippers/haircutting-capes/', 'https://www.shavershop.com.au/pet-clippers/', 'https://www.shavershop.com.au/men/head-shavers/', 'https://www.shavershop.com.au/men/head-shavers/', 'https://www.shavershop.com.au/men/head-shavers/all-head-shavers/', 'https://www.shavershop.com.au/men/head-shavers/parts-accessories/', 'https://www.shavershop.com.au/body-groomers/', 'https://www.shavershop.com.au/body-groomers/', 'https://www.shavershop.com.au/body-groomers/all-body-groomers/', 'https://www.shavershop.com.au/blade-shavers/', 'https://www.shavershop.com.au/blade-shavers/', 'https://www.shavershop.com.au/blade-shavers/mens-blade-shaver/', 'https://www.shavershop.com.au/blade-shavers/mens-razor-blades/', 'https://www.shavershop.com.au/blade-shavers/post-shave-accessories/', 'https://www.shavershop.com.au/blade-shavers/pre-shave-accessories/', 'https://www.shavershop.com.au/blade-shavers/shave-brushes/', 'https://www.shavershop.com.au/blade-shavers/shave-sets/', 'https://www.shavershop.com.au/blade-shavers/cut-throats/', 'javascript:void(0)', 'https://www.shavershop.com.au/oral-care-2/', 'https://www.shavershop.com.au/oral-care-2/', 'https://www.shavershop.com.au/oral-care/electric-toothbrushes/', 'https://www.shavershop.com.au/oral-care/water-flossers/', 'https://www.shavershop.com.au/oral-care/toothbrush-refills/', 'https://www.shavershop.com.au/oral-care/toothpaste/', 'https://www.shavershop.com.au/men/oral-b-io/', 'https://www.shavershop.com.au/massage-exercise/', 'https://www.shavershop.com.au/massage-exercise/', 'https://www.shavershop.com.au/massage-exercise/massage-guns/', 'https://www.shavershop.com.au/massage-exercise/back-massage/', 'https://www.shavershop.com.au/massage-exercise/neck-massage/', 'https://www.shavershop.com.au/massage-exercise/feet-massage/', 'https://www.shavershop.com.au/massage-exercise/hand-held-massage/', 'https://www.shavershop.com.au/massage-exercise/mats-rollers/', 'https://www.shavershop.com.au/men/skin-hair-care/', 'https://www.shavershop.com.au/men/skin-hair-care/', 'https://www.shavershop.com.au/men/cologne-aftershave/', 'https://www.shavershop.com.au/men/skin-hair-care/pre-post-shave-skin-care/', 'https://www.shavershop.com.au/men/skin-hair-care/beard-oils-balms-brushes/', 'https://www.shavershop.com.au/men/skin-hair-care/hair-dryers/', 'https://www.shavershop.com.au/men/skin-hair-care/hair-styling-finishing/', 'https://www.shavershop.com.au/men/skin-hair-care/accessories/', 'https://www.shavershop.com.au/women/', 'https://www.shavershop.com.au/ladies-hair-removal/', 'https://www.shavershop.com.au/ladies-hair-removal/', 'https://www.shavershop.com.au/ladies-hair-removal/electric-shavers/', 'https://www.shavershop.com.au/ladies-hair-removal/epilators/', 'https://www.shavershop.com.au/ladies-hair-removal/ladies-blades/', 'https://www.shavershop.com.au/ladies-hair-removal/light-based/', 'https://www.shavershop.com.au/ladies-hair-removal/bikini-trimmers/', 'https://www.shavershop.com.au/hair-styling/', 'https://www.shavershop.com.au/hair-styling/', 'https://www.shavershop.com.au/hair-styling/curlers/', 'https://www.shavershop.com.au/hair-styling/hair-dryers/', 'https://www.shavershop.com.au/hair-styling/straighteners/', 'https://www.shavershop.com.au/hair-styling/stylers/', 'https://www.shavershop.com.au/women/hair-styling/hot-brushes/', 'https://www.shavershop.com.au/women/hair-styling/hair-brushes/', 'https://www.shavershop.com.au/hair-styling/scissors/', 'https://www.shavershop.com.au/women/hair-styling/styling-finishing/', 'https://www.shavershop.com.au/hair-styling/shampoo-conditioner/', 'javascript:void(0)', 'https://www.shavershop.com.au/ladies-beauty/', 'https://www.shavershop.com.au/ladies-beauty/', 'https://www.shavershop.com.au/ladies-skin-care/', 'https://www.shavershop.com.au/ladies-foot-care/', 'https://www.shavershop.com.au/ladies-mirrors/', 'https://www.shavershop.com.au/ladies-manicure-sets/', 'https://www.shavershop.com.au/ladies-oral-care/', 'https://www.shavershop.com.au/ladies-oral-care/', 'https://www.shavershop.com.au/ladies-oral-care/electric-toothbrushes/', 'https://www.shavershop.com.au/ladies-oral-care/water-flossers/', 'https://www.shavershop.com.au/ladies-oral-care/refills-accessories/', 'https://www.shavershop.com.au/women/oral-care/whitening/', 'https://www.shavershop.com.au/ladies-oral-care/toothpaste/', 'https://www.shavershop.com.au/women/oral-b-io/', 'https://www.shavershop.com.au/ladies-massage-exercise/', 'https://www.shavershop.com.au/ladies-massage-exercise/', 'https://www.shavershop.com.au/ladies-massage-exercise/massage-guns/', 'https://www.shavershop.com.au/ladies-massage-exercise/back-massage/', 'https://www.shavershop.com.au/ladies-massage-exercise/neck-massage/', 'https://www.shavershop.com.au/ladies-massage-exercise/feet-massage/', 'https://www.shavershop.com.au/ladies-massage-exercise/hand-held-massage/', 'https://www.shavershop.com.au/ladies-massage-exercise/mats-rollers/', 'https://www.shavershop.com.au/women/fragrance/', 'https://www.shavershop.com.au/women/fragrance/', 'https://www.shavershop.com.au/women/fragrance/fragrance/', 'https://www.shavershop.com.au/brands/', 'https://www.shavershop.com.au/brands/braun/', 'https://www.shavershop.com.au/brands/oral-b/', 'https://www.shavershop.com.au/brands/philips/', 'https://www.shavershop.com.au/brands/vs-sassoon/', 'https://www.shavershop.com.au/brands/remington/', 'https://www.shavershop.com.au/brands/ghd/', 'https://www.shavershop.com.au/brands/therabody/', 'https://www.shavershop.com.au/brands/guard-grooming/', 'https://www.shavershop.com.au/brands/panasonic/', 'https://www.shavershop.com.au/blogheader/', 'https://www.shavershop.com.au/discover/', 'https://www.shavershop.com.au/discover/discover%3A-oral-b-io/', 'https://www.shavershop.com.au/discover/discover%3A-therabody/', 'https://www.shavershop.com.au/discover/discover%3A-flair/', 'https://www.shavershop.com.au/discover/discover%3A-ghd/', 'https://www.shavershop.com.au/discover/discover%3A-cloud-nine/', 'https://www.shavershop.com.au/discover/discover%3A-philips/', 'https://www.shavershop.com.au/discover/discover%3A-braun-pro-9plus/', 'https://www.shavershop.com.au/discover/discover%3A-reduit/', 'https://www.shavershop.com.au/clickcollect', '', 'https://www.shavershop.com.au/sale/', 'https://www.shavershop.com.au/brands/skull-shaver/pitbull-head-shaver/', 'https://www.shavershop.com.au/search', 'https://www.shavershop.com.au/braun/series-9-proplus-wet--and-dry-electric-shaver-with-6-in-1-smartcare-centre--and-travel-case-012353.html', 'https://www.shavershop.com.au/ghd/max-wide-plate-hair-straightener-festive-gift-set---limited-edition-012388.html', 'https://www.shavershop.com.au/braun/silk-expert-pro-5-ipl-latest-generation-long-term-permanent-hair-removal-device-with-2-precision-heads-011431.html', 'https://www.shavershop.com.au/braun/silk-expert-pro-5-ipl-long-term-hair-removal-device-010371.html', 'https://www.shavershop.com.au/braun/series-5-10-in-1-all-in-one-waterproof-style-grooming-kit-012423.html', 'https://www.shavershop.com.au/oral-b/smart-5-5000-electric-toothbrush-009962.html', 'https://www.shavershop.com.au/search', 'https://www.shavershop.com.au/sale/', 'https://www.shavershop.com.au/braun/silk-expert-pro-5-ipl-latest-generation-long-term-permanent-hair-removal-device-with-2-precision-heads-011431.html', 'https://www.shavershop.com.au/brands/braun/', 'https://www.shavershop.com.au/braun/silk-expert-pro-5-ipl-latest-generation-long-term-permanent-hair-removal-device-with-2-precision-heads-011431.html', 'https://www.shavershop.com.au/braun/series-9-proplus-wet--and-dry-electric-shaver-with-6-in-1-smartcare-centre--and-travel-case-012353.html', 'https://www.shavershop.com.au/brands/braun/', 'https://www.shavershop.com.au/braun/series-9-proplus-wet--and-dry-electric-shaver-with-6-in-1-smartcare-centre--and-travel-case-012353.html', 'https://www.shavershop.com.au/oral-b/genius-ai-electric-toothbrush-with-3-replacement-heads--and-smart-travel-case-black-010597.html', 'https://www.shavershop.com.au/brands/oral-b/', 'https://www.shavershop.com.au/oral-b/genius-ai-electric-toothbrush-with-3-replacement-heads--and-smart-travel-case-black-010597.html', 'https://www.shavershop.com.au/silver-bullet/easy-glider-corded-hair-clipper-010776.html', 'https://www.shavershop.com.au/search', 'https://www.shavershop.com.au/silver-bullet/easy-glider-corded-hair-clipper-010776.html', 'https://www.shavershop.com.au/cloud-nine/the-retro-iron---motel-sunset-mandarin-012568.html', 'https://www.shavershop.com.au/brands/cloud-nine/', 'https://www.shavershop.com.au/cloud-nine/the-retro-iron---motel-sunset-mandarin-012568.html', 'https://www.shavershop.com.au/braun/series-7-17-in-1-all-in-one-waterproof-style-grooming-kit-with-premium-travel-case-and-charging-stand-012421.html', 'https://www.shavershop.com.au/brands/braun/', 'https://www.shavershop.com.au/braun/series-7-17-in-1-all-in-one-waterproof-style-grooming-kit-with-premium-travel-case-and-charging-stand-012421.html', 'https://www.shavershop.com.au/therabody/theragun-mini-2.0-black-percussive-therapy-012282.html', 'https://www.shavershop.com.au/brands/therabody/', 'https://www.shavershop.com.au/therabody/theragun-mini-2.0-black-percussive-therapy-012282.html', 'https://www.shavershop.com.au/waterpik/cordless-select-water-flosser---white-010712.html', 'https://www.shavershop.com.au/brands/waterpik/', 'https://www.shavershop.com.au/waterpik/cordless-select-water-flosser---white-010712.html', 'https://www.shavershop.com.au/skull-shaver/one-lion-silver-pro-face-and-head-shaver-012460.html', 'https://www.shavershop.com.au/remington/quick-groom-body--and-back-groomer-010152.html', 'https://www.shavershop.com.au/cutting-edge-sale/oral-care/oral-b-refills/', '/electric-shavers/all-electric-shavers/', '/oral-care-2/', '/massage-exercise/', '/ladies-hair-removal/', '/hair-clippers/', '/hair-styling/', 'https://www.shavershop.com.au/brands/braun/', 'https://www.shavershop.com.au/brands/oral-b/', 'https://www.shavershop.com.au/brands/gillette/', 'https://www.shavershop.com.au/brands/skull-shaver/', 'https://www.shavershop.com.au/brands/ghd/', 'https://www.shavershop.com.au/brands/vs-sassoon/', 'https://www.shavershop.com.au/brands/cloud-nine/', 'https://www.shavershop.com.au/brands/panasonic/', 'https://www.shavershop.com.au/brands/therabody/', 'https://www.shavershop.com.au/brands/flair/', 'https://www.shavershop.com.au/brands/american-crew/', 'https://www.shavershop.com.au/brands/philips/', 'https://www.shavershop.com.au/brands/', '/blog/meet_ghd_s_power_couples___get_more_out_of_your_st', '/blog/beauty_hair', '/blog/meet_ghd_s_power_couples___get_more_out_of_your_st', '/blog/how_to__pick_the_right_panasonic_electric_shaver_f', '/blog/shaving_grooming', '/blog/how_to__pick_the_right_panasonic_electric_shaver_f', '/blog/introducing_chronos__ghd_s_most_advanced_styler_ye', '/blog/beauty_hair', '/blog/introducing_chronos__ghd_s_most_advanced_styler_ye', '/blog/create_curly_hairstyles_for_any_occasion_with_ghd_', '/blog/beauty_hair', '/blog/create_curly_hairstyles_for_any_occasion_with_ghd_', '/blog/meet_ghd_s_power_couples___get_more_out_of_your_st', '/blog/beauty_hair', '/blog/meet_ghd_s_power_couples___get_more_out_of_your_st', '/blog/how_to__pick_the_right_panasonic_electric_shaver_f', '/blog/shaving_grooming', '/blog/how_to__pick_the_right_panasonic_electric_shaver_f', '/blog/introducing_chronos__ghd_s_most_advanced_styler_ye', '/blog/beauty_hair', '/blog/introducing_chronos__ghd_s_most_advanced_styler_ye', '#', 'http://www.facebook.com/shavershop', 'http://www.instagram.com/shavershopau/', 'https://www.linkedin.com/company/shaver-shop', 'https://twitter.com/shavershop', 'http://youtube.com/shavershopau', 'https://www.pinterest.com/shavershop/', 'https://www.shavershop.com.au/contactus', 'https://www.shavershop.com.au/return-and-exchanges.html', 'https://www.shavershop.com.au/giftcertpurchase', 'https://www.shavershop.com.au/delivery.html', 'https://www.shavershop.com.au/clickcollect', 'https://www.shavershop.com.au/terms.html', 'https://investors.shavershop.com.au/', 'https://www.shavershop.com.au/about-history.html', 'https://www.shavershop.com.au/jobs-landing.html', 'https://www.shavershop.com.au/privacy-policy.html']",
    "images": "https://www.shavershop.com.au/on/demandware.static/-/Sites/default/dw19846c6b/images/header-banner/shipping-car.svg, https://www.shavershop.com.au/on/demandware.static/-/Sites/default/dw19846c6b/images/header-banner/shipping-car.svg, https://www.shavershop.com.au/on/demandware.static/-/Sites/default/dw19846c6b/images/header-banner/shipping-car.svg, , , , , , , , , , , , , , , , , , , , , , , , , , , , , , , , , , , , , , , , , , , , , , , , , , , , , , , , , https://www.shavershop.com.au/on/demandware.static/-/Library-Sites-ShaverShopSharedLibrary/default/dw9d42f811/images/dot.png, https://www.shavershop.com.au/on/demandware.static/-/Library-Sites-ShaverShopSharedLibrary/default/dw9d42f811/images/dot.png, https://www.shavershop.com.au/on/demandware.static/-/Library-Sites-ShaverShopSharedLibrary/default/dw9d42f811/images/dot.png, https://www.shavershop.com.au/on/demandware.static/-/Library-Sites-ShaverShopSharedLibrary/default/dw9d42f811/images/dot.png, , , , , , , , , , , , , , , , , , , , , , , , null, null, null, , , null, null, null, null, null, , null, , , , , , , , , , , , , , , , , , , , , , , , , , , , ",
    "company_logo_link": "https://www.shavershop.com.au/on/demandware.static/-/Sites/default/dw19846c6b/images/header-banner/shipping-car.svg"
}