{
    "company_name": "FENIX RESOURCES LTD",
    "address": "Office 10, Emerald House, 1202 Hay St, WEST PERTH, WA, AUSTRALIA, 6005",
    "summary": "Western Australian iron ore producer",
    "details": "Western Australian iron ore producer",
    "website": "http://www.fenixresources.com.au",
    "stock_code": "FEX",
    "links": "['#msite-navigation', '#content', 'https://fenixresources.com.au/', 'https://fenixresources.com.au/mid-west/', 'https://fenixresources.com.au/project-partners/', '', 'https://fenixresources.com.au/company-overview/', 'https://fenixresources.com.au/board-of-directors/', 'https://fenixresources.com.au/corporate-governance/', 'https://fenixresources.com.au/corporate-directory/', '', 'https://fenixresources.com.au/why-invest/', 'https://fenixresources.com.au/share-price-information/', 'https://fenixresources.com.au/asx-announcements/', 'https://fenixresources.com.au/company-presentation/', 'https://fenixresources.com.au/reports/', 'https://fenixresources.com.au/research/', 'https://fenixresources.com.au/share-registry/', 'https://fenixresources.com.au/subscribe/', '', 'https://fenixresources.com.au/community/', 'https://fenixresources.com.au/environment/', '#', 'https://fenixresources.com.au/media/videos/', 'https://fenixresources.com.au/media/articles/', 'https://fenixresources.com.au/media/image-gallery/', 'https://fenixresources.com.au/contact-us/', 'https://www.linkedin.com/company/68972158/', 'https://twitter.com/Fenix_Resources', 'https://fenixresources.com.au/', 'https://fenixresources.com.au/mid-west/', 'https://www2.asx.com.au/markets/company/FEX', '/wp-content/uploads/2023/12/AGMPresentation24Nov23.pdf#new_tab', 'https://fenixresources.com.au/category/presentations/', '/wp-content/uploads/2023/12/AGMPresentation24Nov23.pdf#new_tab', 'https://fenixresources.com.au/author/dannika/', '/wp-content/uploads/2023/12/AGMPresentation24Nov23.pdf#new_tab', '/wp-content/uploads/2024/03/MSTAcessFEXStrongFirstHalfGrowthAddsValue-21Mar24.pdf#new_tab', 'https://fenixresources.com.au/category/research/', '/wp-content/uploads/2024/03/MSTAcessFEXStrongFirstHalfGrowthAddsValue-21Mar24.pdf#new_tab', 'https://fenixresources.com.au/author/troppusadmin/', '/wp-content/uploads/2024/03/MSTAcessFEXStrongFirstHalfGrowthAddsValue-21Mar24.pdf#new_tab', 'http://fenixresources-com-au.stackstaging.com/contact-us/', 'https://fenixresources.com.au/company-overview/', 'https://fenixresources.com.au/board-of-directors/', 'https://fenixresources.com.au/corporate-governance/', 'https://fenixresources.com.au/corporate-directory/', 'https://fenixresources.com.au/employees/', 'https://fenixresources.com.au/why-invest/', 'https://fenixresources.com.au/share-price-information/', 'https://fenixresources.com.au/asx-announcements/', 'https://fenixresources.com.au/company-presentation/', 'https://fenixresources.com.au/reports/', 'https://fenixresources.com.au/research/', 'https://fenixresources.com.au/share-registry/', 'https://fenixresources.com.au/media/', 'https://fenixresources.com.au/subscribe/', 'https://fenixresources.com.au/environment/', 'https://fenixresources.com.au/community/', 'https://fenixresources.com.au/privacy-policy/', 'Tel:08 9226 2011', '/cdn-cgi/l/email-protection#30595e565f7056555e59484255435f45425355431e535f5d1e5145', 'https://www.linkedin.com/company/68972158/', 'https://twitter.com/Fenix_Resources', '#']",
    "images": "https://fenixresources.com.au/wp-content/uploads/2022/04/Fenix-Logo_RGB.png, https://fenixresources.com.au/wp-content/uploads/2022/05/Picture-1.jpg, https://fenixresources.com.au/wp-content/uploads/2022/05/Picture-1.jpg, https://fenixresources.com.au/wp-content/uploads/2023/11/1698973812466-300x143.jpg, https://fenixresources.com.au/wp-content/uploads/2023/12/Thumbnail2023AGMPresentation24Nov23-700x540.jpg, https://fenixresources.com.au/wp-content/uploads/2024/03/ThumbnailMSTAcessFEXStrongFirstHalf21Mar24-1-700x540.jpg",
    "company_logo_link": "https://fenixresources.com.au/wp-content/uploads/2022/04/Fenix-Logo_RGB.png"
}