{
    "company_name": "CONTROL BIONICS LIMITED",
    "address": "Level 4 11 Pearson Street, CREMORNE, VIC, AUSTRALIA, 3121",
    "summary": "Technology company that designs, manufactures and sells augmentative and alternative communication technology that allows users to operate and communicate via computer using their thoughts and neural signals",
    "details": "Technology company that designs, manufactures and sells augmentative and alternative communication technology that allows users to operate and communicate via computer using their thoughts and neural signals",
    "website": "https://www.controlbionics.com/",
    "stock_code": "CBL",
    "links": "['#content', 'https://www.controlbionics.com/products/', 'https://www.controlbionics.com/who-we-help/', 'https://www.controlbionics.com/funding/', 'https://www.controlbionics.com/tech-support/', 'https://www.controlbionics.com/tech-support/', 'https://www.controlbionics.com/tech-support/grid-3-support/', 'https://www.controlbionics.com/products/', 'https://www.controlbionics.com/products/how-it-works/', 'https://www.controlbionics.com/products/the-neuronode-trilogy-aus/', 'https://www.controlbionics.com/products/the-neuronode-duo-aus/', 'https://www.controlbionics.com/products/the-eyegaze-duo-aus/', 'https://www.controlbionics.com/products/the-uno-touch-aus/', 'https://www.controlbionics.com/products/the-cosmos-connect/', 'https://www.controlbionics.com/products/the-neuronode/', 'https://www.controlbionics.com/products/drove/', 'https://www.controlbionics.com/connection-center/', 'https://www.controlbionics.com/connection-center/', 'https://www.controlbionics.com/connection-center/downloadable-vocabulary/', 'https://www.controlbionics.com/connection-center/for-clinicians-aus/', 'https://www.controlbionics.com/connection-center/past-webinars-and-trainings/', 'https://www.controlbionics.com/category/general/', 'https://www.controlbionics.com/control-bionics-company/', 'https://www.controlbionics.com/control-bionics-company/', 'https://www.controlbionics.com/for-investors/', 'https://www.controlbionics.com/available-positions/', 'https://www.controlbionics.com/news-blog/', 'https://www.controlbionics.com/terms-and-conditions/', 'https://www.controlbionics.com/contact-us/', 'https://www.controlbionics.com/who-we-help/', 'https://www.controlbionics.com/funding/', 'https://www.controlbionics.com/tech-support/', 'https://www.controlbionics.com/tech-support/', 'https://www.controlbionics.com/tech-support/grid-3-support/', 'https://www.controlbionics.com/products/', 'https://www.controlbionics.com/products/how-it-works/', 'https://www.controlbionics.com/products/the-neuronode-trilogy-aus/', 'https://www.controlbionics.com/products/the-neuronode-duo-aus/', 'https://www.controlbionics.com/products/the-eyegaze-duo-aus/', 'https://www.controlbionics.com/products/the-uno-touch-aus/', 'https://www.controlbionics.com/products/the-cosmos-connect/', 'https://www.controlbionics.com/products/the-neuronode/', 'https://www.controlbionics.com/products/drove/', 'https://www.controlbionics.com/connection-center/', 'https://www.controlbionics.com/connection-center/', 'https://www.controlbionics.com/connection-center/downloadable-vocabulary/', 'https://www.controlbionics.com/connection-center/for-clinicians-aus/', 'https://www.controlbionics.com/connection-center/past-webinars-and-trainings/', 'https://www.controlbionics.com/category/general/', 'https://www.controlbionics.com/control-bionics-company/', 'https://www.controlbionics.com/control-bionics-company/', 'https://www.controlbionics.com/for-investors/', 'https://www.controlbionics.com/available-positions/', 'https://www.controlbionics.com/news-blog/', 'https://www.controlbionics.com/terms-and-conditions/', 'https://www.controlbionics.com/contact-us/', 'https://www.controlbionics.com', 'https://www.controlbionics.com/products/', 'https://www.controlbionics.com', 'https://www.facebook.com/ControlBionics', 'https://www.instagram.com/controlbionics', 'https://twitter.com/control_bionics', 'https://www.linkedin.com/company/control-bionics/', 'https://www.youtube.com/user/controlbionics/videos', 'https://www.controlbionics.com/who-we-help/', 'https://www.controlbionics.com/funding/', 'https://www.controlbionics.com/tech-support/', 'https://www.controlbionics.com/tech-support/', 'https://www.controlbionics.com/tech-support/grid-3-support/', 'https://www.controlbionics.com/products/', 'https://www.controlbionics.com/products/how-it-works/', 'https://www.controlbionics.com/products/the-neuronode-trilogy-aus/', 'https://www.controlbionics.com/products/the-neuronode-duo-aus/', 'https://www.controlbionics.com/products/the-eyegaze-duo-aus/', 'https://www.controlbionics.com/products/the-uno-touch-aus/', 'https://www.controlbionics.com/products/the-cosmos-connect/', 'https://www.controlbionics.com/products/the-neuronode/', 'https://www.controlbionics.com/products/drove/', 'https://www.controlbionics.com/connection-center/', 'https://www.controlbionics.com/connection-center/', 'https://www.controlbionics.com/connection-center/downloadable-vocabulary/', 'https://www.controlbionics.com/connection-center/for-clinicians-aus/', 'https://www.controlbionics.com/connection-center/past-webinars-and-trainings/', 'https://www.controlbionics.com/category/general/', 'https://www.controlbionics.com/control-bionics-company/', 'https://www.controlbionics.com/control-bionics-company/', 'https://www.controlbionics.com/for-investors/', 'https://www.controlbionics.com/available-positions/', 'https://www.controlbionics.com/news-blog/', 'https://www.controlbionics.com/contact-us/', 'https://www.controlbionics.com/who-we-help/', 'https://www.controlbionics.com/funding/', 'https://www.controlbionics.com/tech-support/', 'https://www.controlbionics.com/tech-support/', 'https://www.controlbionics.com/tech-support/grid-3-support/', 'https://www.controlbionics.com/products/', 'https://www.controlbionics.com/products/how-it-works/', 'https://www.controlbionics.com/products/the-neuronode-trilogy-aus/', 'https://www.controlbionics.com/products/the-neuronode-duo-aus/', 'https://www.controlbionics.com/products/the-eyegaze-duo-aus/', 'https://www.controlbionics.com/products/the-uno-touch-aus/', 'https://www.controlbionics.com/products/the-cosmos-connect/', 'https://www.controlbionics.com/products/the-neuronode/', 'https://www.controlbionics.com/products/drove/', 'https://www.controlbionics.com/connection-center/', 'https://www.controlbionics.com/connection-center/', 'https://www.controlbionics.com/connection-center/downloadable-vocabulary/', 'https://www.controlbionics.com/connection-center/for-clinicians-aus/', 'https://www.controlbionics.com/connection-center/past-webinars-and-trainings/', 'https://www.controlbionics.com/category/general/', 'https://www.controlbionics.com/control-bionics-company/', 'https://www.controlbionics.com/control-bionics-company/', 'https://www.controlbionics.com/for-investors/', 'https://www.controlbionics.com/available-positions/', 'https://www.controlbionics.com/news-blog/', 'https://www.controlbionics.com/contact-us/', 'https://controlbionics.com/products', 'https://www.controlbionics.com/products/', 'https://www.controlbionics.com/products/', 'https://www.controlbionics.com/products/the-neuronode-trilogy-aus/', 'https://www.controlbionics.com/products/the-neuronode-trilogy-aus', 'https://www.controlbionics.com/products/the-neuronode-duo-aus/', 'https://www.controlbionics.com/products/the-neuronode-duo-aus', 'https://www.controlbionics.com/products/the-eyegaze-duo-aus/', 'https://www.controlbionics.com/products/the-eyegaze-duo-aus', 'https://www.controlbionics.com/products/the-uno-touch-aus/', 'https://www.controlbionics.com/products/the-uno-touch-aus', 'https://www.controlbionics.com/products/the-neuronode/', 'https://www.controlbionics.com/products/the-neuronode/', 'https://www.controlbionics.com/products/the-cosmos-connect/', 'https://www.controlbionics.com/products/the-cosmos-connect/', 'https://www.controlbionics.com/products/how-it-works/', 'https://www.controlbionics.com/products/the-neuronode/', 'https://youtu.be/6QIpx7otugE', 'https://youtu.be/TMUnPrNd8VI', 'https://youtu.be/p_AFGTRaJXs', 'https://www.controlbionics.com/who-we-help/', 'https://www.controlbionics.com/connection-center/', 'https://www.controlbionics.com/2024/the-als-assocation-awards-a-prestigious-assistive-technology-grant-to-control-bionics/', 'https://www.controlbionics.com/2023/introducing-control-bionics-champion-max-bailey/', 'https://www.controlbionics.com/2023/myth-v-fact-series-1/', 'https://www.controlbionics.com/category/general/', '/', 'https://www.facebook.com/ControlBionics', 'https://www.instagram.com/controlbionics/', 'https://twitter.com/control_bionics', 'https://www.linkedin.com/company/control-bionics/', 'https://www.youtube.com/user/controlbionics/videos', 'https://www.controlbionics.com/news-blog/', 'https://store.controlbionics.com/', 'https://www.controlbionics.com/available-positions/', 'https://www.controlbionics.com/terms-and-conditions/', 'https://www.controlbionics.com/wp-content/uploads/2023/01/Privacy-Policy-010523.pdf', 'https://www.controlbionics.com/contact-us/', 'https://www.controlbionics.com/news-blog/', 'https://store.controlbionics.com/', 'https://www.controlbionics.com/available-positions/', 'https://www.controlbionics.com/terms-and-conditions/', 'https://www.controlbionics.com/wp-content/uploads/2023/01/Privacy-Policy-010523.pdf', 'https://www.controlbionics.com/contact-us/', 'https://controlbionics.co.jp/']",
    "images": "https://www.controlbionics.com/wp-content/uploads/2021/08/Control-Bionics-Logo-2021B-1500-300x93.png, https://www.controlbionics.com/wp-content/uploads/2021/08/Control-Bionics-Logo-2021B-1500-300x93.png, data:image/gif;base64,R0lGODlhAQABAIAAAAAAAP///yH5BAEAAAAALAAAAAABAAEAAAIBRAA7, https://www.controlbionics.com/wp-content/uploads/2024/03/free-trial-draft-left-1024x337.png, data:image/gif;base64,R0lGODlhAQABAIAAAAAAAP///yH5BAEAAAAALAAAAAABAAEAAAIBRAA7, https://www.controlbionics.com/wp-content/uploads/2024/03/free-trial-better2-right-1024x338.png, data:image/gif;base64,R0lGODlhAQABAIAAAAAAAP///yH5BAEAAAAALAAAAAABAAEAAAIBRAA7, https://www.controlbionics.com/wp-content/uploads/2022/12/trilogy-with-logo-and-grid.png, data:image/gif;base64,R0lGODlhAQABAIAAAAAAAP///yH5BAEAAAAALAAAAAABAAEAAAIBRAA7, https://www.controlbionics.com/wp-content/uploads/2022/11/nn-duo-with-logo-and-grid-1.png, data:image/gif;base64,R0lGODlhAQABAIAAAAAAAP///yH5BAEAAAAALAAAAAABAAEAAAIBRAA7, https://www.controlbionics.com/wp-content/uploads/2022/11/eyegaze-with-logo-and-grid-1.png, data:image/gif;base64,R0lGODlhAQABAIAAAAAAAP///yH5BAEAAAAALAAAAAABAAEAAAIBRAA7, https://www.controlbionics.com/wp-content/uploads/2022/11/uno-with-logo-and-grid-1.png, data:image/gif;base64,R0lGODlhAQABAIAAAAAAAP///yH5BAEAAAAALAAAAAABAAEAAAIBRAA7, https://www.controlbionics.com/wp-content/uploads/2022/12/NN-919x1024.png, data:image/gif;base64,R0lGODlhAQABAIAAAAAAAP///yH5BAEAAAAALAAAAAABAAEAAAIBRAA7, https://www.controlbionics.com/wp-content/uploads/2022/12/Cosmos-920x1024.png, data:image/gif;base64,R0lGODlhAQABAIAAAAAAAP///yH5BAEAAAAALAAAAAABAAEAAAIBRAA7, https://www.controlbionics.com/wp-content/uploads/2021/03/Header-Products-NN3.png, data:image/gif;base64,R0lGODlhAQABAIAAAAAAAP///yH5BAEAAAAALAAAAAABAAEAAAIBRAA7, https://www.controlbionics.com/wp-content/uploads/2022/12/Neuronode-Trilogy_Rev_K-300x56.png, data:image/gif;base64,R0lGODlhAQABAIAAAAAAAP///yH5BAEAAAAALAAAAAABAAEAAAIBRAA7, https://www.controlbionics.com/wp-content/uploads/2022/12/Tag-Line-300x106.png, data:image/gif;base64,R0lGODlhAQABAIAAAAAAAP///yH5BAEAAAAALAAAAAABAAEAAAIBRAA7, https://www.controlbionics.com/wp-content/uploads/2022/12/maree-play-1024x576.png, data:image/gif;base64,R0lGODlhAQABAIAAAAAAAP///yH5BAEAAAAALAAAAAABAAEAAAIBRAA7, https://www.controlbionics.com/wp-content/uploads/2022/12/ian-play-1024x576.png, data:image/gif;base64,R0lGODlhAQABAIAAAAAAAP///yH5BAEAAAAALAAAAAABAAEAAAIBRAA7, https://www.controlbionics.com/wp-content/uploads/2022/12/ryan-play-1024x578.png, data:image/gif;base64,R0lGODlhAQABAIAAAAAAAP///yH5BAEAAAAALAAAAAABAAEAAAIBRAA7, https://www.controlbionics.com/wp-content/uploads/2022/04/IMG_9365-scaled.jpg, data:image/gif;base64,R0lGODlhAQABAIAAAAAAAP///yH5BAEAAAAALAAAAAABAAEAAAIBRAA7, data:image/gif;base64,R0lGODlhAQABAIAAAAAAAP///yH5BAEAAAAALAAAAAABAAEAAAIBRAA7, https://www.controlbionics.com/wp-content/uploads/2024/02/alsa-default-card-new.jpg, data:image/gif;base64,R0lGODlhAQABAIAAAAAAAP///yH5BAEAAAAALAAAAAABAAEAAAIBRAA7, data:image/gif;base64,R0lGODlhAQABAIAAAAAAAP///yH5BAEAAAAALAAAAAABAAEAAAIBRAA7, https://www.controlbionics.com/wp-content/uploads/2023/07/max-screenshot-604x340-16x9-1.jpg, data:image/gif;base64,R0lGODlhAQABAIAAAAAAAP///yH5BAEAAAAALAAAAAABAAEAAAIBRAA7, data:image/gif;base64,R0lGODlhAQABAIAAAAAAAP///yH5BAEAAAAALAAAAAABAAEAAAIBRAA7, https://www.controlbionics.com/wp-content/uploads/2023/06/NN-e1687555370122-978x550-16-9.jpg, https://www.controlbionics.com/wp-content/uploads/2021/08/Control-Bionics-Logo_tag-2021B-1500-300x141.png",
    "company_logo_link": "https://www.controlbionics.com/wp-content/uploads/2021/08/Control-Bionics-Logo-2021B-1500-300x93.png"
}